README.md
setup.cfg
setup.py
dataviper/__init__.py
dataviper/categorical_column.py
dataviper/client.py
dataviper.egg-info/PKG-INFO
dataviper.egg-info/SOURCES.txt
dataviper.egg-info/dependency_links.txt
dataviper.egg-info/requires.txt
dataviper.egg-info/top_level.txt
dataviper/logger/__init__.py
dataviper/report/__init__.py
dataviper/report/histogram.py
dataviper/report/joinability.py
dataviper/report/profile.py
dataviper/report/utils.py
dataviper/source/__init__.py
dataviper/source/csv.py
dataviper/source/datasource.py
dataviper/source/mysql.py
dataviper/source/sqlserver.py
tests/__init__.py
tests/client_test.py
tests/story_test.py