Metadata-Version: 2.1
Name: dataviper
Version: 0.1.6
Summary: A simple Data Quality Assessment Tool based on SQL
Home-page: https://github.com/otiai10/dataviper
Author: Hiromu Ochiai
Author-email: otiai10@gmail.com
License: UNKNOWN
Platform: UNKNOWN
Classifier: Programming Language :: Python :: 3
Classifier: License :: OSI Approved :: MIT License
